ssid_scanner/__init__.py
ssid_scanner/ssid_scanner.py
ssid_scanner-0.1.0.dist-info/LICENSE
ssid_scanner-0.1.0.dist-info/METADATA
ssid_scanner-0.1.0.dist-info/WHEEL
ssid_scanner-0.1.0.dist-info/top_level.txt
ssid_scanner-0.1.0.dist-info/RECORD
