Metadata-Version: 2.1
Name: ssid-scanner
Version: 0.1.0
Summary: A package for scanning nearby wireless access points on Linux machines.
Home-page: https://gitlab.com/ae-ou/ssid_scanner
Author: ae-ou
Author-email: UNKNOWN
License: UNKNOWN
Platform: UNKNOWN
Classifier: Programming Language :: Python :: 3
Classifier: Operating System :: POSIX :: Linux
Classifier: License :: Other/Proprietary License
Classifier: Topic :: System :: Networking
Requires-Dist: pyric (==0.1.6.3)
Requires-Dist: wifi (==0.3.8)
